pychecksumtool/__init__.py
pychecksumtool/_version.py
pychecksumtool/cachedchecksum.py
pychecksumtool/checksum.py
pychecksumtool/hashalgorithm.py
pychecksumtool/hashcache.py
pychecksumtool/scripts/__init__.py
pychecksumtool/scripts/clichecksum.py
pychecksumtool-0.1.5.dist-info/LICENSE
pychecksumtool-0.1.5.dist-info/METADATA
pychecksumtool-0.1.5.dist-info/WHEEL
pychecksumtool-0.1.5.dist-info/entry_points.txt
pychecksumtool-0.1.5.dist-info/RECORD
