Metadata-Version: 2.1
Name: pychecksumtool
Version: 0.1.5
Summary: A generalised efficient checksum library for python hashlib
License: Apache-2.0
Author: Joe Drumgoole
Author-email: joe@joedrumgoole.com
Requires-Python: >=3.12,<4.0
Classifier: License :: OSI Approved :: Apache Software License
Classifier: Programming Language :: Python :: 3
Classifier: Programming Language :: Python :: 3.12
Requires-Dist: pytest (>=8.3.4,<9.0.0)
Requires-Dist: typer (>=0.15.2,<0.16.0)
